{
  "minecraft:recipes/building_blocks/polished_granite_stairs": {
    "criteria": {
      "has_polished_granite": "2024-03-16 21:21:49 +0200"
    },
    "done": true
  },
  "minecraft:recipes/building_blocks/polished_granite_stairs_from_polished_granite_stonecutting": {
    "criteria": {
      "has_polished_granite": "2024-03-16 21:21:49 +0200"
    },
    "done": true
  },
  "minecraft:recipes/decorations/crafting_table": {
    "criteria": {
      "unlock_right_away": "2024-03-16 21:21:01 +0200"
    },
    "done": true
  },
  "minecraft:adventure/adventuring_time": {
    "criteria": {
      "minecraft:plains": "2024-03-16 21:21:02 +0200"
    },
    "done": false
  },
  "minecraft:recipes/building_blocks/polished_granite_slab_from_polished_granite_stonecutting": {
    "criteria": {
      "has_polished_granite": "2024-03-16 21:21:49 +0200"
    },
    "done": true
  },
  "minecraft:recipes/building_blocks/polished_granite_slab": {
    "criteria": {
      "has_polished_granite": "2024-03-16 21:21:49 +0200"
    },
    "done": true
  },
  "DataVersion": 3700
}